tcl_kernel/__init__.py
tcl_kernel/__main__.py
tcl_kernel/install.py
tcl_kernel/kernel.json
tcl_kernel/kernel.py
tcl_kernel-0.0.5.dist-info/LICENSE.md
tcl_kernel-0.0.5.dist-info/WHEEL
tcl_kernel-0.0.5.dist-info/METADATA
tcl_kernel-0.0.5.dist-info/RECORD
