Metadata-Version: 2.1
Name: tcl_kernel
Version: 0.0.5
Summary: A Tcl kernel for Jupyter
Home-page: https://github.com/ryanpepper/tcl_kernel
License: UNKNOWN
Author: Ryan Pepper
Author-email: rp20g15@soton.ac.uk
Classifier: Framework :: IPython
Classifier: License :: OSI Approved :: BSD License
Classifier: Programming Language :: Python :: 3
Classifier: Topic :: System :: Shells
Requires-Dist: pexpect (>=3.3)
